xenopy/__init__.py
xenopy/query.py
xenopy/utils.py
xenopy-0.0.4.dist-info/LICENSE
xenopy-0.0.4.dist-info/METADATA
xenopy-0.0.4.dist-info/WHEEL
xenopy-0.0.4.dist-info/top_level.txt
xenopy-0.0.4.dist-info/RECORD
