Metadata-Version: 2.1
Name: xenopy
Version: 0.0.4
Summary: The most straightforward and efficient python wrapper for xeno-canto API 2.0
Home-page: https://github.com/realzza/xenopy
Author: Ziang Zhou
Author-email: ziang.zhou518@gmail.com
License: UNKNOWN
Project-URL: Bug Tracker, https://github.com/realzza/xenopy/issues
Platform: UNKNOWN
Classifier: Programming Language :: Python :: 3
Classifier: License :: OSI Approved :: GNU General Public License v3 or later (GPLv3+)
Classifier: Operating System :: OS Independent
Requires-Python: >=3.6
License-File: LICENSE
Requires-Dist: tqdm
Requires-Dist: multiprocess
